aioazuredevops/__init__.py
aioazuredevops/client.py
aioazuredevops/helper.py
aioazuredevops/models/__init__.py
aioazuredevops/models/build.py
aioazuredevops/models/core.py
aioazuredevops/models/iteration.py
aioazuredevops/models/iteration_work_item.py
aioazuredevops/models/wiql.py
aioazuredevops/models/work_item.py
aioazuredevops/models/work_item_type.py
aioazuredevops-2.2.2.dist-info/licenses/LICENSE
aioazuredevops-2.2.2.dist-info/METADATA
aioazuredevops-2.2.2.dist-info/WHEEL
aioazuredevops-2.2.2.dist-info/top_level.txt
aioazuredevops-2.2.2.dist-info/RECORD
