Metadata-Version: 2.4
Name: aioazuredevops
Version: 2.2.2
Summary: Get data from the Azure DevOps API
Home-page: https://github.com/timmo001/aioazuredevops
Author: Aidan Timson (Timmo)
Author-email: aidan@timmo.dev
License: Apache-2.0
Keywords: aioazuredevops,api,async,asyncio,azure devops,devops,integration
Requires-Python: >=3.11
License-File: LICENSE
Requires-Dist: aiohttp>=3.12.15
Dynamic: author
Dynamic: author-email
Dynamic: description
Dynamic: description-content-type
Dynamic: home-page
Dynamic: keywords
Dynamic: license
Dynamic: license-file
Dynamic: requires-dist
Dynamic: requires-python
Dynamic: summary
